setup.py
jsonschematypes/__init__.py
jsonschematypes/factory.py
jsonschematypes/files.py
jsonschematypes/model.py
jsonschematypes/modules.py
jsonschematypes/registry.py
jsonschematypes.egg-info/PKG-INFO
jsonschematypes.egg-info/SOURCES.txt
jsonschematypes.egg-info/dependency_links.txt
jsonschematypes.egg-info/requires.txt
jsonschematypes.egg-info/top_level.txt