Metadata-Version: 1.0
Name: jsonschematypes
Version: 0.5
Summary: JSON Schema type generator
Home-page: http://www.locationlabs.com
Author: Location Labs
Author-email: info@locationlabs.com
License: UNKNOWN
Platform: UNKNOWN
